HbaseShujukuRumenjiaochengCYuyanBianchengWangFix1/README.md
HbaseShujukuRumenjiaochengCYuyanBianchengWangFix1/__init__.py
HbaseShujukuRumenjiaochengCYuyanBianchengWangFix1/__main__.py
HbaseShujukuRumenjiaochengCYuyanBianchengWangFix1/file.epub
HbaseShujukuRumenjiaochengCYuyanBianchengWangFix1/index.html
HbaseShujukuRumenjiaochengCYuyanBianchengWangFix1/css/__init__.py
HbaseShujukuRumenjiaochengCYuyanBianchengWangFix1/css/annotations.css
HbaseShujukuRumenjiaochengCYuyanBianchengWangFix1/css/main.css
HbaseShujukuRumenjiaochengCYuyanBianchengWangFix1/css/normalize.css
HbaseShujukuRumenjiaochengCYuyanBianchengWangFix1/css/popup.css
HbaseShujukuRumenjiaochengCYuyanBianchengWangFix1/font/__init__.py
HbaseShujukuRumenjiaochengCYuyanBianchengWangFix1/font/fontello.eot
HbaseShujukuRumenjiaochengCYuyanBianchengWangFix1/font/fontello.svg
HbaseShujukuRumenjiaochengCYuyanBianchengWangFix1/font/fontello.ttf
HbaseShujukuRumenjiaochengCYuyanBianchengWangFix1/font/fontello.woff
HbaseShujukuRumenjiaochengCYuyanBianchengWangFix1/img/__init__.py
HbaseShujukuRumenjiaochengCYuyanBianchengWangFix1/img/annotator-glyph-sprite.png
HbaseShujukuRumenjiaochengCYuyanBianchengWangFix1/img/annotator-icon-sprite.png
HbaseShujukuRumenjiaochengCYuyanBianchengWangFix1/img/apple-touch-icon.png
HbaseShujukuRumenjiaochengCYuyanBianchengWangFix1/img/cancelfullscreen.png
HbaseShujukuRumenjiaochengCYuyanBianchengWangFix1/img/close.png
HbaseShujukuRumenjiaochengCYuyanBianchengWangFix1/img/fullscreen.png
HbaseShujukuRumenjiaochengCYuyanBianchengWangFix1/img/loader.gif
HbaseShujukuRumenjiaochengCYuyanBianchengWangFix1/img/menu-icon.png
HbaseShujukuRumenjiaochengCYuyanBianchengWangFix1/img/save.png
HbaseShujukuRumenjiaochengCYuyanBianchengWangFix1/img/saved.png
HbaseShujukuRumenjiaochengCYuyanBianchengWangFix1/img/settings-s.png
HbaseShujukuRumenjiaochengCYuyanBianchengWangFix1/img/settings.png
HbaseShujukuRumenjiaochengCYuyanBianchengWangFix1/img/star.png
hbase_shujuku_rumenjiaocheng_c_yuyan_biancheng_wang_fix1-2025.3.24.0.dist-info/METADATA
hbase_shujuku_rumenjiaocheng_c_yuyan_biancheng_wang_fix1-2025.3.24.0.dist-info/WHEEL
hbase_shujuku_rumenjiaocheng_c_yuyan_biancheng_wang_fix1-2025.3.24.0.dist-info/entry_points.txt
hbase_shujuku_rumenjiaocheng_c_yuyan_biancheng_wang_fix1-2025.3.24.0.dist-info/top_level.txt
hbase_shujuku_rumenjiaocheng_c_yuyan_biancheng_wang_fix1-2025.3.24.0.dist-info/RECORD
